<?xml version="1.0" encoding="UTF-8"?>
<document reference="suspicious-document02956.txt">
  <feature name="about" authors="Tylor, Edward Burnett" title="Anahuac : or, Mexico and the Mexicans, Ancient and Modern" lang="en" />
  <feature name="md5Hash" value="b7f6202cb8923aa92af79090603816eb" />
  <feature name="plagiarism" type="translation" manual_obfuscation="false" this_language="en" this_offset="3794" this_length="21123" source_reference="source-document07910.txt" source_language="de" source_offset="205695" source_length="23873" />
  <feature name="plagiarism" type="translation" manual_obfuscation="false" this_language="en" this_offset="62303" this_length="19173" source_reference="source-document07910.txt" source_language="de" source_offset="339880" source_length="22154" />
  <feature name="plagiarism" type="translation" manual_obfuscation="false" this_language="en" this_offset="99694" this_length="2649" source_reference="source-document03222.txt" source_language="de" source_offset="548810" source_length="3059" />
  <feature name="plagiarism" type="translation" manual_obfuscation="false" this_language="en" this_offset="116140" this_length="14833" source_reference="source-document07910.txt" source_language="de" source_offset="747003" source_length="16864" />
  <feature name="plagiarism" type="translation" manual_obfuscation="false" this_language="en" this_offset="145017" this_length="13270" source_reference="source-document07910.txt" source_language="de" source_offset="820001" source_length="14983" />
  <feature name="plagiarism" type="translation" manual_obfuscation="false" this_language="en" this_offset="171234" this_length="1868" source_reference="source-document00908.txt" source_language="de" source_offset="1500" source_length="2033" />
  <feature name="plagiarism" type="translation" manual_obfuscation="false" this_language="en" this_offset="175004" this_length="709" source_reference="source-document07910.txt" source_language="de" source_offset="425868" source_length="809" />
  <feature name="plagiarism" type="translation" manual_obfuscation="false" this_language="en" this_offset="179574" this_length="4147" source_reference="source-document01799.txt" source_language="de" source_offset="101166" source_length="4779" />
  <feature name="plagiarism" type="translation" manual_obfuscation="false" this_language="en" this_offset="193925" this_length="14029" source_reference="source-document03222.txt" source_language="de" source_offset="271717" source_length="16475" />
  <feature name="plagiarism" type="translation" manual_obfuscation="false" this_language="en" this_offset="224803" this_length="4159" source_reference="source-document03222.txt" source_language="de" source_offset="240406" source_length="4978" />
  <feature name="plagiarism" type="translation" manual_obfuscation="false" this_language="en" this_offset="244755" this_length="18765" source_reference="source-document07910.txt" source_language="de" source_offset="856526" source_length="20983" />
  <feature name="plagiarism" type="translation" manual_obfuscation="false" this_language="en" this_offset="275236" this_length="712" source_reference="source-document01799.txt" source_language="de" source_offset="57978" source_length="804" />
  <feature name="plagiarism" type="translation" manual_obfuscation="false" this_language="en" this_offset="277011" this_length="493" source_reference="source-document01799.txt" source_language="de" source_offset="466113" source_length="527" />
</document>

