<?xml version="1.0" encoding="UTF-8"?>
<document reference="suspicious-document06147.txt">
  <feature name="about" authors="Marryat, Frederick" title="The Privateer's-Man One hundred Years Ago" lang="en" />
  <feature name="md5Hash" value="854a76b8d09879e90606bcc2ff8b619c" />
  <feature name="plagiarism" type="artificial" obfuscation="low" this_language="en" this_offset="4369" this_length="19335" source_reference="source-document00517.txt" source_language="en" source_offset="117" source_length="18243" />
  <feature name="plagiarism" type="artificial" obfuscation="low" this_language="en" this_offset="33253" this_length="24634" source_reference="source-document10384.txt" source_language="en" source_offset="629860" source_length="24515" />
  <feature name="plagiarism" type="artificial" obfuscation="low" this_language="en" this_offset="58881" this_length="4411" source_reference="source-document05422.txt" source_language="en" source_offset="6013" source_length="4517" />
  <feature name="plagiarism" type="artificial" obfuscation="low" this_language="en" this_offset="68973" this_length="12083" source_reference="source-document06516.txt" source_language="en" source_offset="4764" source_length="16739" />
  <feature name="plagiarism" type="artificial" obfuscation="low" this_language="en" this_offset="88123" this_length="20744" source_reference="source-document10384.txt" source_language="en" source_offset="176692" source_length="20792" />
  <feature name="plagiarism" type="artificial" obfuscation="low" this_language="en" this_offset="112351" this_length="16201" source_reference="source-document10384.txt" source_language="en" source_offset="716914" source_length="16695" />
  <feature name="plagiarism" type="artificial" obfuscation="low" this_language="en" this_offset="131554" this_length="1968" source_reference="source-document06516.txt" source_language="en" source_offset="129" source_length="1974" />
  <feature name="plagiarism" type="artificial" obfuscation="low" this_language="en" this_offset="135038" this_length="16802" source_reference="source-document10384.txt" source_language="en" source_offset="81480" source_length="16482" />
  <feature name="plagiarism" type="artificial" obfuscation="low" this_language="en" this_offset="163415" this_length="20629" source_reference="source-document10384.txt" source_language="en" source_offset="409123" source_length="24465" />
  <feature name="plagiarism" type="artificial" obfuscation="low" this_language="en" this_offset="185547" this_length="19895" source_reference="source-document10384.txt" source_language="en" source_offset="343141" source_length="19550" />
  <feature name="plagiarism" type="artificial" obfuscation="low" this_language="en" this_offset="217762" this_length="19213" source_reference="source-document10384.txt" source_language="en" source_offset="662819" source_length="23543" />
  <feature name="plagiarism" type="artificial" obfuscation="low" this_language="en" this_offset="238841" this_length="1739" source_reference="source-document03541.txt" source_language="en" source_offset="0" source_length="1740" />
  <feature name="plagiarism" type="artificial" obfuscation="low" this_language="en" this_offset="242043" this_length="5014" source_reference="source-document05422.txt" source_language="en" source_offset="873" source_length="5029" />
  <feature name="plagiarism" type="artificial" obfuscation="low" this_language="en" this_offset="250372" this_length="15850" source_reference="source-document10384.txt" source_language="en" source_offset="108284" source_length="15210" />
  <feature name="plagiarism" type="artificial" obfuscation="low" this_language="en" this_offset="274015" this_length="22132" source_reference="source-document10384.txt" source_language="en" source_offset="457237" source_length="23293" />
  <feature name="plagiarism" type="artificial" obfuscation="low" this_language="en" this_offset="299042" this_length="3469" source_reference="source-document10384.txt" source_language="en" source_offset="297266" source_length="3457" />
  <feature name="plagiarism" type="artificial" obfuscation="low" this_language="en" this_offset="311076" this_length="26605" source_reference="source-document10384.txt" source_language="en" source_offset="143176" source_length="25072" />
  <feature name="plagiarism" type="artificial" obfuscation="low" this_language="en" this_offset="343698" this_length="24316" source_reference="source-document10384.txt" source_language="en" source_offset="538044" source_length="24499" />
  <feature name="plagiarism" type="artificial" obfuscation="low" this_language="en" this_offset="370792" this_length="1769" source_reference="source-document10384.txt" source_language="en" source_offset="277740" source_length="1810" />
  <feature name="plagiarism" type="artificial" obfuscation="low" this_language="en" this_offset="372562" this_length="1757" source_reference="source-document03541.txt" source_language="en" source_offset="1975" source_length="1700" />
  <feature name="plagiarism" type="artificial" obfuscation="low" this_language="en" this_offset="375441" this_length="3797" source_reference="source-document10384.txt" source_language="en" source_offset="738193" source_length="3780" />
  <feature name="plagiarism" type="artificial" obfuscation="low" this_language="en" this_offset="381178" this_length="4051" source_reference="source-document10384.txt" source_language="en" source_offset="320273" source_length="4242" />
  <feature name="plagiarism" type="artificial" obfuscation="low" this_language="en" this_offset="387253" this_length="16795" source_reference="source-document10384.txt" source_language="en" source_offset="750280" source_length="19281" />
  <feature name="plagiarism" type="artificial" obfuscation="low" this_language="en" this_offset="411797" this_length="19564" source_reference="source-document10384.txt" source_language="en" source_offset="244944" source_length="18851" />
  <feature name="plagiarism" type="artificial" obfuscation="low" this_language="en" this_offset="438444" this_length="22985" source_reference="source-document10384.txt" source_language="en" source_offset="219787" source_length="23063" />
  <feature name="plagiarism" type="artificial" obfuscation="low" this_language="en" this_offset="465325" this_length="4409" source_reference="source-document10384.txt" source_language="en" source_offset="400158" source_length="4472" />
  <feature name="plagiarism" type="artificial" obfuscation="low" this_language="en" this_offset="471167" this_length="24116" source_reference="source-document10384.txt" source_language="en" source_offset="39532" source_length="23494" />
  <feature name="plagiarism" type="artificial" obfuscation="low" this_language="en" this_offset="508417" this_length="21578" source_reference="source-document10384.txt" source_language="en" source_offset="434766" source_length="21668" />
  <feature name="plagiarism" type="artificial" obfuscation="low" this_language="en" this_offset="532812" this_length="14232" source_reference="source-document10384.txt" source_language="en" source_offset="19095" source_length="15070" />
  <feature name="plagiarism" type="artificial" obfuscation="low" this_language="en" this_offset="554078" this_length="21077" source_reference="source-document10384.txt" source_language="en" source_offset="371917" source_length="22806" />
  <feature name="plagiarism" type="artificial" obfuscation="low" this_language="en" this_offset="582963" this_length="19213" source_reference="source-document10384.txt" source_language="en" source_offset="512948" source_length="18663" />
  <feature name="plagiarism" type="artificial" obfuscation="low" this_language="en" this_offset="605135" this_length="242" source_reference="source-document03541.txt" source_language="en" source_offset="1740" source_length="235" />
  <feature name="plagiarism" type="artificial" obfuscation="low" this_language="en" this_offset="605529" this_length="3737" source_reference="source-document10384.txt" source_language="en" source_offset="334902" source_length="3720" />
  <feature name="plagiarism" type="artificial" obfuscation="low" this_language="en" this_offset="611491" this_length="4959" source_reference="source-document10384.txt" source_language="en" source_offset="773914" source_length="4990" />
  <feature name="plagiarism" type="artificial" obfuscation="low" this_language="en" this_offset="617329" this_length="226" source_reference="source-document05422.txt" source_language="en" source_offset="648" source_length="225" />
  <feature name="plagiarism" type="artificial" obfuscation="low" this_language="en" this_offset="617811" this_length="2666" source_reference="source-document06516.txt" source_language="en" source_offset="2103" source_length="2661" />
  <feature name="plagiarism" type="artificial" obfuscation="low" this_language="en" this_offset="621126" this_length="528" source_reference="source-document00517.txt" source_language="en" source_offset="18681" source_length="479" />
</document>

