<?xml version="1.0" encoding="UTF-8"?>
<document reference="suspicious-document06005.txt">
  <feature name="about" authors="Peck, George Wilbur" title="How Private George W. Peck Put Down The Rebellion or, The Funny Experiences of a Raw Recruit - 1887" lang="en" />
  <feature name="md5Hash" value="808fef31f45b7cec2a47c33fda891449" />
  <feature name="plagiarism" type="artificial" obfuscation="high" this_language="en" this_offset="10980" this_length="3598" source_reference="source-document02617.txt" source_language="en" source_offset="195510" source_length="4647" />
  <feature name="plagiarism" type="artificial" obfuscation="high" this_language="en" this_offset="22900" this_length="527" source_reference="source-document02617.txt" source_language="en" source_offset="1448" source_length="545" />
  <feature name="plagiarism" type="artificial" obfuscation="high" this_language="en" this_offset="59157" this_length="10691" source_reference="source-document06451.txt" source_language="en" source_offset="158501" source_length="15022" />
  <feature name="plagiarism" type="artificial" obfuscation="high" this_language="en" this_offset="105694" this_length="2879" source_reference="source-document07279.txt" source_language="en" source_offset="833230" source_length="3694" />
  <feature name="plagiarism" type="artificial" obfuscation="high" this_language="en" this_offset="179310" this_length="9655" source_reference="source-document02617.txt" source_language="en" source_offset="169380" source_length="17642" />
  <feature name="plagiarism" type="artificial" obfuscation="high" this_language="en" this_offset="193308" this_length="2720" source_reference="source-document07279.txt" source_language="en" source_offset="334831" source_length="3021" />
  <feature name="plagiarism" type="artificial" obfuscation="high" this_language="en" this_offset="209967" this_length="736" source_reference="source-document07279.txt" source_language="en" source_offset="410998" source_length="756" />
  <feature name="plagiarism" type="artificial" obfuscation="high" this_language="en" this_offset="263628" this_length="7486" source_reference="source-document07279.txt" source_language="en" source_offset="930322" source_length="17755" />
  <feature name="plagiarism" type="artificial" obfuscation="high" this_language="en" this_offset="360783" this_length="19154" source_reference="source-document07279.txt" source_language="en" source_offset="253175" source_length="22961" />
  <feature name="plagiarism" type="artificial" obfuscation="high" this_language="en" this_offset="403589" this_length="1811" source_reference="source-document02617.txt" source_language="en" source_offset="267436" source_length="1953" />
  <feature name="plagiarism" type="artificial" obfuscation="high" this_language="en" this_offset="422216" this_length="4693" source_reference="source-document07279.txt" source_language="en" source_offset="885971" source_length="4792" />
  <feature name="plagiarism" type="artificial" obfuscation="high" this_language="en" this_offset="437950" this_length="750" source_reference="source-document07279.txt" source_language="en" source_offset="434453" source_length="736" />
  <feature name="plagiarism" type="artificial" obfuscation="high" this_language="en" this_offset="440832" this_length="422" source_reference="source-document02617.txt" source_language="en" source_offset="158657" source_length="453" />
  <feature name="plagiarism" type="artificial" obfuscation="high" this_language="en" this_offset="448314" this_length="2358" source_reference="source-document02617.txt" source_language="en" source_offset="63415" source_length="2642" />
  <feature name="plagiarism" type="artificial" obfuscation="high" this_language="en" this_offset="462753" this_length="3184" source_reference="source-document06451.txt" source_language="en" source_offset="33098" source_length="2977" />
  <feature name="plagiarism" type="artificial" obfuscation="high" this_language="en" this_offset="471147" this_length="671" source_reference="source-document02617.txt" source_language="en" source_offset="291673" source_length="696" />
</document>

