<?xml version="1.0" encoding="UTF-8"?>
<document reference="suspicious-document04862.txt">
  <feature name="about" authors="Wright, Mabel Osgood" title="People of the Whirlpool" lang="en" />
  <feature name="md5Hash" value="6ad0d55a168fe8e7b4a52c6f31ba753a" />
  <feature name="plagiarism" type="translation" manual_obfuscation="false" this_language="en" this_offset="1" this_length="4016" source_reference="source-document10050.txt" source_language="de" source_offset="8947" source_length="4531" />
  <feature name="plagiarism" type="translation" manual_obfuscation="false" this_language="en" this_offset="4788" this_length="2575" source_reference="source-document10050.txt" source_language="de" source_offset="752" source_length="2970" />
  <feature name="plagiarism" type="translation" manual_obfuscation="false" this_language="en" this_offset="7364" this_length="1788" source_reference="source-document10050.txt" source_language="de" source_offset="20107" source_length="1981" />
  <feature name="plagiarism" type="translation" manual_obfuscation="false" this_language="en" this_offset="9304" this_length="688" source_reference="source-document10050.txt" source_language="de" source_offset="8184" source_length="755" />
  <feature name="plagiarism" type="translation" manual_obfuscation="false" this_language="en" this_offset="9993" this_length="1382" source_reference="source-document10050.txt" source_language="de" source_offset="13778" source_length="1586" />
  <feature name="plagiarism" type="translation" manual_obfuscation="false" this_language="en" this_offset="11376" this_length="416" source_reference="source-document10050.txt" source_language="de" source_offset="6818" source_length="517" />
  <feature name="plagiarism" type="translation" manual_obfuscation="false" this_language="en" this_offset="11793" this_length="413" source_reference="source-document10050.txt" source_language="de" source_offset="16878" source_length="465" />
  <feature name="plagiarism" type="translation" manual_obfuscation="false" this_language="en" this_offset="12207" this_length="219" source_reference="source-document10050.txt" source_language="de" source_offset="275" source_length="230" />
  <feature name="plagiarism" type="translation" manual_obfuscation="false" this_language="en" this_offset="12427" this_length="205" source_reference="source-document10050.txt" source_language="de" source_offset="13541" source_length="237" />
  <feature name="plagiarism" type="translation" manual_obfuscation="false" this_language="en" this_offset="12838" this_length="630" source_reference="source-document10050.txt" source_language="de" source_offset="3890" source_length="728" />
</document>

