<?xml version="1.0" encoding="UTF-8"?>
<document reference="suspicious-document04695.txt">
  <feature name="about" authors="Luther, Martin" title="Epistle Sermons, Vol. II Epiphany, Easter and Pentecost" lang="en" />
  <feature name="md5Hash" value="a72fc8fb453bb0e45076bc83b5b01785" />
  <feature name="plagiarism" type="artificial" obfuscation="high" this_language="en" this_offset="1417" this_length="19373" source_reference="source-document02216.txt" source_language="en" source_offset="47996" source_length="20694" />
  <feature name="plagiarism" type="artificial" obfuscation="high" this_language="en" this_offset="25632" this_length="18547" source_reference="source-document07486.txt" source_language="en" source_offset="135473" source_length="18762" />
  <feature name="plagiarism" type="artificial" obfuscation="high" this_language="en" this_offset="48179" this_length="17910" source_reference="source-document07486.txt" source_language="en" source_offset="58390" source_length="20268" />
  <feature name="plagiarism" type="artificial" obfuscation="high" this_language="en" this_offset="69091" this_length="16090" source_reference="source-document02216.txt" source_language="en" source_offset="129158" source_length="16232" />
  <feature name="plagiarism" type="artificial" obfuscation="high" this_language="en" this_offset="86017" this_length="22342" source_reference="source-document02216.txt" source_language="en" source_offset="149917" source_length="24289" />
  <feature name="plagiarism" type="artificial" obfuscation="high" this_language="en" this_offset="113283" this_length="19623" source_reference="source-document02216.txt" source_language="en" source_offset="222176" source_length="21361" />
  <feature name="plagiarism" type="artificial" obfuscation="high" this_language="en" this_offset="136305" this_length="15991" source_reference="source-document07486.txt" source_language="en" source_offset="117699" source_length="16050" />
  <feature name="plagiarism" type="artificial" obfuscation="high" this_language="en" this_offset="155057" this_length="17507" source_reference="source-document02216.txt" source_language="en" source_offset="75052" source_length="20679" />
  <feature name="plagiarism" type="artificial" obfuscation="high" this_language="en" this_offset="177005" this_length="15350" source_reference="source-document02216.txt" source_language="en" source_offset="196547" source_length="15279" />
  <feature name="plagiarism" type="artificial" obfuscation="high" this_language="en" this_offset="193422" this_length="4912" source_reference="source-document07486.txt" source_language="en" source_offset="34905" source_length="4991" />
  <feature name="plagiarism" type="artificial" obfuscation="high" this_language="en" this_offset="201397" this_length="15066" source_reference="source-document02216.txt" source_language="en" source_offset="100482" source_length="15138" />
  <feature name="plagiarism" type="artificial" obfuscation="high" this_language="en" this_offset="219637" this_length="13911" source_reference="source-document02216.txt" source_language="en" source_offset="19892" source_length="14950" />
  <feature name="plagiarism" type="artificial" obfuscation="high" this_language="en" this_offset="236085" this_length="20930" source_reference="source-document02216.txt" source_language="en" source_offset="175064" source_length="21483" />
  <feature name="plagiarism" type="artificial" obfuscation="high" this_language="en" this_offset="260435" this_length="14341" source_reference="source-document02216.txt" source_language="en" source_offset="243860" source_length="15479" />
  <feature name="plagiarism" type="artificial" obfuscation="high" this_language="en" this_offset="276360" this_length="21731" source_reference="source-document07486.txt" source_language="en" source_offset="1311" source_length="22252" />
  <feature name="plagiarism" type="artificial" obfuscation="high" this_language="en" this_offset="302350" this_length="14583" source_reference="source-document07486.txt" source_language="en" source_offset="40129" source_length="15515" />
  <feature name="plagiarism" type="artificial" obfuscation="high" this_language="en" this_offset="319197" this_length="9343" source_reference="source-document07486.txt" source_language="en" source_offset="81137" source_length="19215" />
  <feature name="plagiarism" type="artificial" obfuscation="high" this_language="en" this_offset="331929" this_length="7397" source_reference="source-document00089.txt" source_language="en" source_offset="66852" source_length="18872" />
  <feature name="plagiarism" type="artificial" obfuscation="high" this_language="en" this_offset="342347" this_length="3916" source_reference="source-document00621.txt" source_language="en" source_offset="0" source_length="3857" />
  <feature name="plagiarism" type="artificial" obfuscation="high" this_language="en" this_offset="348613" this_length="11036" source_reference="source-document06527.txt" source_language="en" source_offset="218" source_length="20207" />
  <feature name="plagiarism" type="artificial" obfuscation="high" this_language="en" this_offset="363990" this_length="10491" source_reference="source-document06334.txt" source_language="en" source_offset="14658" source_length="20278" />
  <feature name="plagiarism" type="artificial" obfuscation="high" this_language="en" this_offset="375125" this_length="3049" source_reference="source-document02216.txt" source_language="en" source_offset="211893" source_length="3051" />
  <feature name="plagiarism" type="artificial" obfuscation="high" this_language="en" this_offset="381802" this_length="4983" source_reference="source-document00089.txt" source_language="en" source_offset="132804" source_length="19795" />
  <feature name="plagiarism" type="artificial" obfuscation="high" this_language="en" this_offset="387104" this_length="1815" source_reference="source-document02216.txt" source_language="en" source_offset="42186" source_length="1918" />
  <feature name="plagiarism" type="artificial" obfuscation="high" this_language="en" this_offset="390867" this_length="12868" source_reference="source-document00089.txt" source_language="en" source_offset="113027" source_length="15284" />
  <feature name="plagiarism" type="artificial" obfuscation="high" this_language="en" this_offset="405328" this_length="3199" source_reference="source-document06527.txt" source_language="en" source_offset="22206" source_length="3466" />
  <feature name="plagiarism" type="artificial" obfuscation="high" this_language="en" this_offset="411182" this_length="15766" source_reference="source-document00089.txt" source_language="en" source_offset="316" source_length="19615" />
  <feature name="plagiarism" type="artificial" obfuscation="high" this_language="en" this_offset="427913" this_length="4149" source_reference="source-document02216.txt" source_language="en" source_offset="37669" source_length="4208" />
  <feature name="plagiarism" type="artificial" obfuscation="high" this_language="en" this_offset="432819" this_length="3941" source_reference="source-document00089.txt" source_language="en" source_offset="27991" source_length="4174" />
  <feature name="plagiarism" type="artificial" obfuscation="high" this_language="en" this_offset="441120" this_length="9446" source_reference="source-document00089.txt" source_language="en" source_offset="184705" source_length="23218" />
  <feature name="plagiarism" type="artificial" obfuscation="high" this_language="en" this_offset="452510" this_length="11776" source_reference="source-document00089.txt" source_language="en" source_offset="32749" source_length="16686" />
  <feature name="plagiarism" type="artificial" obfuscation="high" this_language="en" this_offset="465818" this_length="2014" source_reference="source-document02216.txt" source_language="en" source_offset="125957" source_length="2010" />
  <feature name="plagiarism" type="artificial" obfuscation="high" this_language="en" this_offset="468456" this_length="15399" source_reference="source-document10377.txt" source_language="en" source_offset="3066" source_length="16126" />
  <feature name="plagiarism" type="artificial" obfuscation="high" this_language="en" this_offset="488288" this_length="19119" source_reference="source-document06334.txt" source_language="en" source_offset="296695" source_length="20558" />
  <feature name="plagiarism" type="artificial" obfuscation="high" this_language="en" this_offset="509088" this_length="18780" source_reference="source-document06334.txt" source_language="en" source_offset="213318" source_length="19609" />
</document>

