<?xml version="1.0" encoding="UTF-8"?>
<document reference="suspicious-document00904.txt">
  <feature name="about" authors="Sweeney, William Allison" title="History of the American Negro in the Great World War His Splendid Record in the Battle Zones of Europe; Including a Resume of His Past Services to his Country in the Wars of the Revolution, of 1812, the War of Rebellion, the Indian Wars on the Frontier, the Spanish-American War, and the Late Imbroglio With Mexico" lang="en" />
  <feature name="md5Hash" value="55b31306311028947270a57b4651c42a" />
  <feature name="plagiarism" type="artificial" obfuscation="low" this_language="en" this_offset="1062" this_length="2801" source_reference="source-document09825.txt" source_language="en" source_offset="235" source_length="3000" />
  <feature name="plagiarism" type="artificial" obfuscation="low" this_language="en" this_offset="12666" this_length="3327" source_reference="source-document04353.txt" source_language="en" source_offset="227595" source_length="3341" />
  <feature name="plagiarism" type="artificial" obfuscation="low" this_language="en" this_offset="49473" this_length="23974" source_reference="source-document06900.txt" source_language="en" source_offset="9503" source_length="22504" />
  <feature name="plagiarism" type="artificial" obfuscation="low" this_language="en" this_offset="93605" this_length="16966" source_reference="source-document06900.txt" source_language="en" source_offset="334939" source_length="18515" />
  <feature name="plagiarism" type="artificial" obfuscation="low" this_language="en" this_offset="167365" this_length="20309" source_reference="source-document06900.txt" source_language="en" source_offset="51690" source_length="20170" />
  <feature name="plagiarism" type="artificial" obfuscation="low" this_language="en" this_offset="224968" this_length="20020" source_reference="source-document06900.txt" source_language="en" source_offset="194950" source_length="19684" />
  <feature name="plagiarism" type="artificial" obfuscation="low" this_language="en" this_offset="266060" this_length="18732" source_reference="source-document06900.txt" source_language="en" source_offset="275928" source_length="18704" />
  <feature name="plagiarism" type="artificial" obfuscation="low" this_language="en" this_offset="318677" this_length="20597" source_reference="source-document06900.txt" source_language="en" source_offset="249373" source_length="20995" />
  <feature name="plagiarism" type="artificial" obfuscation="low" this_language="en" this_offset="365285" this_length="3367" source_reference="source-document09825.txt" source_language="en" source_offset="3235" source_length="3540" />
  <feature name="plagiarism" type="artificial" obfuscation="low" this_language="en" this_offset="374268" this_length="265" source_reference="source-document09825.txt" source_language="en" source_offset="8842" source_length="250" />
  <feature name="plagiarism" type="artificial" obfuscation="low" this_language="en" this_offset="375392" this_length="239" source_reference="source-document09825.txt" source_language="en" source_offset="9761" source_length="234" />
</document>

