<?xml version="1.0" encoding="UTF-8"?>
<document reference="suspicious-document02310.txt">
  <feature name="about" authors="Wilson, Harry Leon" title="Merton of the Movies" lang="en" />
  <feature name="md5Hash" value="2f7865af104dbeaaa4df4ebcf5ee9653" />
  <feature name="plagiarism" type="artificial" obfuscation="low" this_language="en" this_offset="761" this_length="18490" source_reference="source-document02631.txt" source_language="en" source_offset="46904" source_length="20011" />
  <feature name="plagiarism" type="artificial" obfuscation="low" this_language="en" this_offset="19808" this_length="15103" source_reference="source-document02099.txt" source_language="en" source_offset="41507" source_length="15760" />
  <feature name="plagiarism" type="artificial" obfuscation="low" this_language="en" this_offset="35584" this_length="2747" source_reference="source-document10088.txt" source_language="en" source_offset="20916" source_length="2716" />
  <feature name="plagiarism" type="artificial" obfuscation="low" this_language="en" this_offset="38852" this_length="17620" source_reference="source-document02099.txt" source_language="en" source_offset="15940" source_length="18447" />
  <feature name="plagiarism" type="artificial" obfuscation="low" this_language="en" this_offset="57088" this_length="21939" source_reference="source-document02099.txt" source_language="en" source_offset="130443" source_length="22513" />
  <feature name="plagiarism" type="artificial" obfuscation="low" this_language="en" this_offset="81067" this_length="14190" source_reference="source-document06524.txt" source_language="en" source_offset="1125" source_length="19008" />
  <feature name="plagiarism" type="artificial" obfuscation="low" this_language="en" this_offset="96191" this_length="15798" source_reference="source-document02631.txt" source_language="en" source_offset="127539" source_length="16462" />
  <feature name="plagiarism" type="artificial" obfuscation="low" this_language="en" this_offset="112794" this_length="22415" source_reference="source-document02099.txt" source_language="en" source_offset="80068" source_length="23518" />
  <feature name="plagiarism" type="artificial" obfuscation="low" this_language="en" this_offset="136034" this_length="14040" source_reference="source-document06524.txt" source_language="en" source_offset="24529" source_length="14908" />
  <feature name="plagiarism" type="artificial" obfuscation="low" this_language="en" this_offset="151112" this_length="18463" source_reference="source-document02099.txt" source_language="en" source_offset="107550" source_length="19678" />
  <feature name="plagiarism" type="artificial" obfuscation="low" this_language="en" this_offset="170548" this_length="17453" source_reference="source-document02099.txt" source_language="en" source_offset="199473" source_length="19316" />
  <feature name="plagiarism" type="artificial" obfuscation="low" this_language="en" this_offset="188540" this_length="18099" source_reference="source-document02631.txt" source_language="en" source_offset="171620" source_length="20260" />
  <feature name="plagiarism" type="artificial" obfuscation="low" this_language="en" this_offset="207997" this_length="17263" source_reference="source-document02099.txt" source_language="en" source_offset="240658" source_length="18326" />
  <feature name="plagiarism" type="artificial" obfuscation="low" this_language="en" this_offset="225830" this_length="18356" source_reference="source-document02099.txt" source_language="en" source_offset="171166" source_length="23509" />
  <feature name="plagiarism" type="artificial" obfuscation="low" this_language="en" this_offset="245537" this_length="3329" source_reference="source-document06524.txt" source_language="en" source_offset="40759" source_length="3505" />
  <feature name="plagiarism" type="artificial" obfuscation="low" this_language="en" this_offset="249152" this_length="3980" source_reference="source-document10088.txt" source_language="en" source_offset="3706" source_length="4025" />
  <feature name="plagiarism" type="artificial" obfuscation="low" this_language="en" this_offset="253559" this_length="17981" source_reference="source-document02099.txt" source_language="en" source_offset="218789" source_length="18892" />
  <feature name="plagiarism" type="artificial" obfuscation="low" this_language="en" this_offset="272477" this_length="3576" source_reference="source-document10088.txt" source_language="en" source_offset="14554" source_length="3737" />
  <feature name="plagiarism" type="artificial" obfuscation="low" this_language="en" this_offset="276150" this_length="1998" source_reference="source-document10088.txt" source_language="en" source_offset="660" source_length="1994" />
  <feature name="plagiarism" type="artificial" obfuscation="low" this_language="en" this_offset="278245" this_length="516" source_reference="source-document02631.txt" source_language="en" source_offset="30699" source_length="516" />
  <feature name="plagiarism" type="artificial" obfuscation="low" this_language="en" this_offset="278830" this_length="458" source_reference="source-document06524.txt" source_language="en" source_offset="53573" source_length="473" />
</document>

